Workbook

Sheet Raw Data
A1: RAMADAN BEVERAGE PROJECT | TRANSACTION LEDGER
A2: Period: Ramadan 1447H (2026) | Data as of 9 March 2026 |
A4: Date | B4: No. | C4: Type | D4: Category | E4: Description | F4: Qty (Unit) | G4: Unit Price (Rp) | H4: Debit (Rp) | I4: Credit (Rp) | J4: Balance (Rp)
A5: 2026-02-25 | B5: 1 | C5: Income | D5: Sales | E5: Beverage Orders | F5: 241 | G5: 4000 | H5: =F5*G5 -> 964000 | I5: 0 | J5: =H5-I5 -> 964000
A6: 2026-02-25 | B6: 2 | C6: Expense | D6: Raw Materials | E6: Sugar | F6: 6 | G6: 16500 | H6: 0 | I6: =F6*G6 -> 99000 | J6: =J5+H6-I6 -> 865000
A7: 2026-02-25 | B7: 3 | C7: Expense | D7: Operational | E7: Cup 18 Oz | F7: 6 | G7: 15000 | H7: 0 | I7: =F7*G7 -> 90000 | J7: =J6+H7-I7 -> 775000
A8: 2026-02-25 | B8: 4 | C8: Expense | D8: Operational | E8: Straw | F8: 1 | G8: 15000 | H8: 0 | I8: =F8*G8 -> 15000 | J8: =J7+H8-I8 -> 760000
A9: 2026-02-25 | B9: 5 | C9: Expense | D9: Raw Materials | E9: Temulawak | F9: 6 | G9: 6000 | H9: 0 | I9: =F9*G9 -> 36000 | J9: =J8+H9-I9 -> 724000
A10: 2026-02-25 | B10: 6 | C10: Expense | D10: Raw Materials | E10: Basil Seed | F10: 2 | G10: 7000 | H10: 0 | I10: =F10*G10 -> 14000 | J10: =J9+H10-I10 -> 710000
A11: 2026-02-25 | B11: 7 | C11: Expense | D11: Operational | E11: Plastic Press | F11: 1 | G11: 20000 | H11: 0 | I11: =F11*G11 -> 20000 | J11: =J10+H11-I11 -> 690000
A12: 2026-02-25 | B12: 8 | C12: Expense | D12: Operational | E12: Water Gallon | F12: 2 | G12: 4500 | H12: 0 | I12: =F12*G12 -> 9000 | J12: =J11+H12-I12 -> 681000
A13: 2026-02-25 | B13: 9 | C13: Expense | D13: Raw Materials | E13: Large Ice Block | F13: 3 | G13: 10000 | H13: 0 | I13: =F13*G13 -> 30000 | J13: =J12+H13-I13 -> 651000
A14: 2026-02-25 | B14: 10 | C14: Expense | D14: Raw Materials | E14: Small Ice Block | F14: 3 | G14: 6000 | H14: 0 | I14: =F14*G14 -> 18000 | J14: =J13+H14-I14 -> 633000
A15: 2026-03-03 | B15: 1 | C15: Income | D15: Sales | E15: Beverage Orders | F15: 261 | G15: 4000 | H15: =F15*G15 -> 1044000 | I15: 0 | J15: =J14+H15-I15 -> 1677000
A16: 2026-03-03 | B16: 2 | C16: Expense | D16: Raw Materials | E16: Sugar | F16: 7 | G16: 16500 | H16: 0 | I16: =F16*G16 -> 115500 | J16: =J15+H16-I16 -> 1561500
A17: 2026-03-03 | B17: 3 | C17: Expense | D17: Raw Materials | E17: Grass Jelly | F17: 15 | G17: 3000 | H17: 0 | I17: =F17*G17 -> 45000 | J17: =J16+H17-I17 -> 1516500
A18: 2026-03-03 | B18: 4 | C18: Expense | D18: Raw Materials | E18: Raspberry Flavor | F18: 2 | G18: 5000 | H18: 0 | I18: =F18*G18 -> 10000 | J18: =J17+H18-I18 -> 1506500
A19: 2026-03-03 | B19: 5 | C19: Expense | D19: Raw Materials | E19: Food Coloring | F19: 1 | G19: 6000 | H19: 0 | I19: =F19*G19 -> 6000 | J19: =J18+H19-I19 -> 1500500
A20: 2026-03-03 | B20: 6 | C20: Expense | D20: Raw Materials | E20: Small Ice Block | F20: 2 | G20: 6000 | H20: 0 | I20: =F20*G20 -> 12000 | J20: =J19+H20-I20 -> 1488500
A21: 2026-03-03 | B21: 7 | C21: Expense | D21: Operational | E21: Cup 14 Oz | F21: 6 | G21: 8000 | H21: 0 | I21: =F21*G21 -> 48000 | J21: =J20+H21-I21 -> 1440500
A22: 2026-03-03 | B22: 8 | C22: Expense | D22: Operational | E22: Straw | F22: 2 | G22: 6000 | H22: 0 | I22: =F22*G22 -> 12000 | J22: =J21+H22-I22 -> 1428500
A23: 2026-03-03 | B23: 9 | C23: Expense | D23: Operational | E23: Water Gallon | F23: 2 | G23: 5000 | H23: 0 | I23: =F23*G23 -> 10000 | J23: =J22+H23-I23 -> 1418500
A24: 2026-03-03 | B24: 10 | C24: Expense | D24: Operational | E24: Gasoline | F24: 1 | G24: 20000 | H24: 0 | I24: =F24*G24 -> 20000 | J24: =J23+H24-I24 -> 1398500
A25: 2026-03-09 | B25: 1 | C25: Income | D25: Sales | E25: Beverage Orders | F25: 261 | G25: 4000 | H25: =F25*G25 -> 1044000 | I25: 0 | J25: =J24+H25-I25 -> 2442500
A26: 2026-03-09 | B26: 2 | C26: Expense | D26: Raw Materials | E26: Sugar | F26: 8 | G26: 16300 | H26: 0 | I26: =F26*G26 -> 130400 | J26: =J25+H26-I26 -> 2312100
A27: 2026-03-09 | B27: 3 | C27: Expense | D27: Raw Materials | E27: Cinnamon | F27: 1 | G27: 12000 | H27: 0 | I27: =F27*G27 -> 12000 | J27: =J26+H27-I27 -> 2300100
A28: 2026-03-09 | B28: 4 | C28: Expense | D28: Operational | E28: Shopping Bag + Parking | F28: 1 | G28: 5000 | H28: 0 | I28: =F28*G28 -> 5000 | J28: =J27+H28-I28 -> 2295100
A29: 2026-03-09 | B29: 5 | C29: Expense | D29: Operational | E29: Cup 16 Oz | F29: 5 | G29: 8000 | H29: 0 | I29: =F29*G29 -> 40000 | J29: =J28+H29-I29 -> 2255100
A30: 2026-03-09 | B30: 6 | C30: Expense | D30: Operational | E30: Straw | F30: 2 | G30: 6000 | H30: 0 | I30: =F30*G30 -> 12000 | J30: =J29+H30-I30 -> 2243100
A31: 2026-03-09 | B31: 7 | C31: Expense | D31: Raw Materials | E31: Banana | F31: 14 | G31: 12143 | H31: 0 | I31: =F31*G31 -> 170002 | J31: =J30+H31-I31 -> 2073098
A32: 2026-03-09 | B32: 8 | C32: Expense | D32: Raw Materials | E32: Clove | F32: 4 | G32: 2000 | H32: 0 | I32: =F32*G32 -> 8000 | J32: =J31+H32-I32 -> 2065098
A33: 2026-03-09 | B33: 9 | C33: Expense | D33: Raw Materials | E33: Large Ice Block | F33: 4 | G33: 10000 | H33: 0 | I33: =F33*G33 -> 40000 | J33: =J32+H33-I33 -> 2025098
A34: 2026-03-09 | B34: 10 | C34: Expense | D34: Labor | E34: Worker Wages | F34: 1 | G34: 50000 | H34: 0 | I34: =F34*G34 -> 50000 | J34: =J33+H34-I34 -> 1975098
A35: 2026-03-09 | B35: 11 | C35: Expense | D35: Operational | E35: Plastic Sealer | F35: 1 | G35: 22500 | H35: 0 | I35: =F35*G35 -> 22500 | J35: =J34+H35-I35 -> 1952598
A36: 2026-03-09 | B36: 12 | C36: Expense | D36: Operational | E36: Water Gallon | F36: 3 | G36: 5000 | H36: 0 | I36: =F36*G36 -> 15000 | J36: =J35+H36-I36 -> 1937598
A38: NOTE: Blue text = hardcoded inputs | Black text = formulas | Green/bold rows = Income entries | Debit = Cash In | Credit = Cash Out | Balance = Running cumulative

Sheet Summary
A1: RAMADAN BEVERAGE PROJECT | FINANCIAL SUMMARY
A2: Ramadan 1447H (2026) | 3 Sessions
A4: Total Revenue (Rp) | C4: Total Cost (Rp) | E4: Net Profit (Rp) | G4: Profit Margin (%)
A5: =SUMIF('Raw Data'!C5:C36,"Income",'Raw Data'!H5:H36) -> 3052000 | C5: =SUMIF('Raw Data'!C5:C36,"Expense",'Raw Data'!I5:I36) -> 1114402 | E5: =A5-C5 -> 1937598 | G5: =IF(A5=0,0,E5/A5) -> 0.63486173
A8: DAILY SESSION SUMMARY
A9: Session Date | B9: Revenue (Rp) | C9: Total Cost (Rp) | D9: Net Profit (Rp) | E9: Margin (%) | F9: Units Sold | G9: Price / Unit (Rp) | H9: Cumulative Profit (Rp)
A10: 25-Feb-2026 | B10: =SUMIFS('Raw Data'!H$5:H$36,'Raw Data'!C$5:C$36,"Income",'Raw Data'!A$5:A$36,DATE(2026,2,25)) -> 964000 | C10: =SUMIFS('Raw Data'!I$5:I$36,'Raw Data'!C$5:C$36,"Expense",'Raw Data'!A$5:A$36,DATE(2026,2,25)) -> 331000 | D10: =B10-C10 -> 633000 | E10: =IF(B10=0,0,D10/B10) -> 0.656639 | F10: =SUMIFS('Raw Data'!F$5:F$36,'Raw Data'!C$5:C$36,"Income",'Raw Data'!A$5:A$36,DATE(2026,2,25)) -> 241 | G10: =IF(F10=0,0,B10/F10) -> 4000 | H10: =SUM(D10:D10) -> 633000
A11: 03-Mar-2026 | B11: =SUMIFS('Raw Data'!H$5:H$36,'Raw Data'!C$5:C$36,"Income",'Raw Data'!A$5:A$36,DATE(2026,3,3)) -> 1044000 | C11: =SUMIFS('Raw Data'!I$5:I$36,'Raw Data'!C$5:C$36,"Expense",'Raw Data'!A$5:A$36,DATE(2026,3,3)) -> 278500 | D11: =B11-C11 -> 765500 | E11: =IF(B11=0,0,D11/B11) -> 0.73323755 | F11: =SUMIFS('Raw Data'!F$5:F$36,'Raw Data'!C$5:C$36,"Income",'Raw Data'!A$5:A$36,DATE(2026,3,3)) -> 261 | G11: =IF(F11=0,0,B11/F11) -> 4000 | H11: =SUM(D10:D11) -> 1398500
A12: 09-Mar-2026 | B12: =SUMIFS('Raw Data'!H$5:H$36,'Raw Data'!C$5:C$36,"Income",'Raw Data'!A$5:A$36,DATE(2026,3,9)) -> 1044000 | C12: =SUMIFS('Raw Data'!I$5:I$36,'Raw Data'!C$5:C$36,"Expense",'Raw Data'!A$5:A$36,DATE(2026,3,9)) -> 504902 | D12: =B12-C12 -> 539098 | E12: =IF(B12=0,0,D12/B12) -> 0.51637739 | F12: =SUMIFS('Raw Data'!F$5:F$36,'Raw Data'!C$5:C$36,"Income",'Raw Data'!A$5:A$36,DATE(2026,3,9)) -> 261 | G12: =IF(F12=0,0,B12/F12) -> 4000 | H12: =SUM(D10:D12) -> 1937598
A13: TOTAL / AVERAGE | B13: =SUM(B10:B12) -> 3052000 | C13: =SUM(C10:C12) -> 1114402 | D13: =SUM(D10:D12) -> 1937598 | E13: =IF(B13=0,0,D13/B13) -> 0.63486173 | F13: =SUM(F10:F12) -> 763 | G13: =IF(F13=0,0,B13/F13) -> 4000 | H13: -
A15: COST BREAKDOWN BY CATEGORY
A16: Category | B16: Total Cost (Rp) | C16: % of Revenue | D16: % of Total Cost
A17: Raw Materials | B17: =SUMIF('Raw Data'!D5:D36,"Raw Materials",'Raw Data'!I5:I36) -> 745902 | C17: =IF(A5=0,0,B17/A5) -> 0.24439777 | D17: =IF(B17+B18+B19=0,0,B17/(B17+B18+B19)) -> 0.66932938
A18: Operational | B18: =SUMIF('Raw Data'!D5:D36,"Operational",'Raw Data'!I5:I36) -> 318500 | C18: =IF(A5=0,0,B18/A5) -> 0.1043578 | D18: =IF(B17+B18+B19=0,0,B18/(B17+B18+B19)) -> 0.28580351
A19: Labor | B19: =SUMIF('Raw Data'!D5:D36,"Labor",'Raw Data'!I5:I36) -> 50000 | C19: =IF(A5=0,0,B19/A5) -> 0.0163827 | D19: =IF(B17+B18+B19=0,0,B19/(B17+B18+B19)) -> 0.044867113
A20: TOTAL | B20: =SUM(B17:B19) -> 1114402 | C20: =IF(A5=0,0,B20/A5) -> 0.36513827 | D20: 1

Sheet Product Analysis
A1: PRODUCT & COST ANALYSIS | Ingredient & Operational Breakdown
A2: Ramadan 1447H (2026) | All Sessions Combined
A4: Category | B4: Item / Description | C4: Total Qty | D4: Last Unit Price (Rp) | E4: Total Cost (Rp) | F4: Frequency | G4: % of Total Cost
A5: Raw Materials | B5: Sugar | C5: 20 | D5: 16300 | E5: 331400 | F5: 3 | G5: =IF(SUM(E5:E25)=0,0,E5/SUM(E5:E25)) -> 0.27827693
A6: Raw Materials | B6: Banana | C6: 14 | D6: 12143 | E6: 170000 | F6: 1 | G6: =IF(SUM(E5:E25)=0,0,E6/SUM(E5:E25)) -> 0.14274918
A7: Raw Materials | B7: Large Ice Block | C7: 11 | D7: 10000 | E7: 110000 | F7: 3 | G7: =IF(SUM(E5:E25)=0,0,E7/SUM(E5:E25)) -> 0.092367117
A8: Raw Materials | B8: Grass Jelly | C8: 15 | D8: 3000 | E8: 45000 | F8: 1 | G8: =IF(SUM(E5:E25)=0,0,E8/SUM(E5:E25)) -> 0.037786548
A9: Raw Materials | B9: Temulawak | C9: 6 | D9: 6000 | E9: 36000 | F9: 1 | G9: =IF(SUM(E5:E25)=0,0,E9/SUM(E5:E25)) -> 0.030229238
A10: Raw Materials | B10: Small Ice Block | C10: 5 | D10: 6000 | E10: 30000 | F10: 2 | G10: =IF(SUM(E5:E25)=0,0,E10/SUM(E5:E25)) -> 0.025191032
A11: Raw Materials | B11: Basil Seed | C11: 2 | D11: 7000 | E11: 14000 | F11: 1 | G11: =IF(SUM(E5:E25)=0,0,E11/SUM(E5:E25)) -> 0.011755815
A12: Raw Materials | B12: Cinnamon | C12: 1 | D12: 12000 | E12: 12000 | F12: 1 | G12: =IF(SUM(E5:E25)=0,0,E12/SUM(E5:E25)) -> 0.010076413
A13: Raw Materials | B13: Clove | C13: 4 | D13: 2000 | E13: 8000 | F13: 1 | G13: =IF(SUM(E5:E25)=0,0,E13/SUM(E5:E25)) -> 0.0067176085
A14: Raw Materials | B14: Raspberry Flavor | C14: 2 | D14: 5000 | E14: 10000 | F14: 1 | G14: =IF(SUM(E5:E25)=0,0,E14/SUM(E5:E25)) -> 0.0083970107
A15: Raw Materials | B15: Food Coloring | C15: 1 | D15: 6000 | E15: 6000 | F15: 1 | G15: =IF(SUM(E5:E25)=0,0,E15/SUM(E5:E25)) -> 0.0050382064
A16: Operational | B16: Cup 18 Oz | C16: 6 | D16: 15000 | E16: 90000 | F16: 1 | G16: =IF(SUM(E5:E25)=0,0,E16/SUM(E5:E25)) -> 0.075573096
A17: Operational | B17: Cup 14 Oz | C17: 6 | D17: 8000 | E17: 48000 | F17: 1 | G17: =IF(SUM(E5:E25)=0,0,E17/SUM(E5:E25)) -> 0.040305651
A18: Operational | B18: Cup 16 Oz | C18: 5 | D18: 8000 | E18: 40000 | F18: 1 | G18: =IF(SUM(E5:E25)=0,0,E18/SUM(E5:E25)) -> 0.033588043
A19: Operational | B19: Straw | C19: 5 | D19: 6000 | E19: 39000 | F19: 3 | G19: =IF(SUM(E5:E25)=0,0,E19/SUM(E5:E25)) -> 0.032748342
A20: Operational | B20: Water Gallon | C20: 7 | D20: 5000 | E20: 34000 | F20: 3 | G20: =IF(SUM(E5:E25)=0,0,E20/SUM(E5:E25)) -> 0.028549836
A21: Operational | B21: Plastic Sealer | C21: 1 | D21: 22500 | E21: 22500 | F21: 1 | G21: =IF(SUM(E5:E25)=0,0,E21/SUM(E5:E25)) -> 0.018893274
A22: Operational | B22: Plastic Press | C22: 1 | D22: 20000 | E22: 20000 | F22: 1 | G22: =IF(SUM(E5:E25)=0,0,E22/SUM(E5:E25)) -> 0.016794021
A23: Operational | B23: Gasoline | C23: 1 | D23: 20000 | E23: 20000 | F23: 1 | G23: =IF(SUM(E5:E25)=0,0,E23/SUM(E5:E25)) -> 0.016794021
A24: Operational | B24: Shopping Bag + Parking | C24: 1 | D24: 5000 | E24: 5000 | F24: 1 | G24: =IF(SUM(E5:E25)=0,0,E24/SUM(E5:E25)) -> 0.0041985053
A25: Labor | B25: Worker Wages | C25: 2 | D25: 50000 | E25: 100000 | F25: 2 | G25: =IF(SUM(E5:E25)=0,0,E25/SUM(E5:E25)) -> 0.083970107
A26: GRAND TOTAL | E26: =SUM(E5:E25) -> 1190900 | G26: 100.0%

Sheet _ChartData
A1: Session | B1: Revenue (Rp) | C1: Total Cost (Rp) | D1: Net Profit (Rp) | E1: Margin (%) | G1: Category | H1: Total Cost (Rp)
A2: 25-Feb | B2: =Summary!B10 -> 964000 | C2: =Summary!C10 -> 331000 | D2: =Summary!D10 -> 633000 | E2: =Summary!E10 -> 0.656639 | G2: Raw Materials | H2: =Summary!B17 -> 745902
A3: 03-Mar | B3: =Summary!B11 -> 1044000 | C3: =Summary!C11 -> 278500 | D3: =Summary!D11 -> 765500 | E3: =Summary!E11 -> 0.73323755 | G3: Operational | H3: =Summary!B18 -> 318500
A4: 09-Mar | B4: =Summary!B12 -> 1044000 | C4: =Summary!C12 -> 504902 | D4: =Summary!D12 -> 539098 | E4: =Summary!E12 -> 0.51637739 | G4: Labor | H4: =Summary!B19 -> 50000

Sheet Dashboard
A1: RAMADAN BEVERAGE PROJECT | MANAGEMENT DASHBOARD
A2: Ramadan 1447H (2026) | 3 Operational Sessions | Data as of: 9 March 2026
A4: Total Revenue | C4: Total Cost | E4: Net Profit | G4: Profit Margin | I4: Units Sold | K4: Avg Order Value
A5: =Summary!A5 -> 3052000 | C5: =Summary!C5 -> 1114402 | E5: =Summary!E5 -> 1937598 | G5: =Summary!G5 -> 0.63486173 | I5: =Summary!F13 -> 763 | K5: =IF(Summary!F13=0,0,Summary!A5/Summary!F13) -> 4000
A6: 3 Sessions Total | C6: All Expenditure | E6: Revenue - Cost | G6: Avg 3 Sessions | I6: Total Cups | K6: Revenue / Unit
A8: Highest Session Profit | E8: Lowest Session Margin | I8: Avg Units / Session | L8: Sessions Analyzed
A9: =MAX(_ChartData!D2:D4) -> 765500 | E9: =MIN(_ChartData!E2:E4) -> 0.51637739 | I9: =AVERAGE(_ChartData!B2:B4)/4000 -> 254.33333 | L9: =COUNTA(_ChartData!A2:A4) -> 3
A12: DAILY SESSION PERFORMANCE (Revenue, Cost & Profit) | H12: COST BREAKDOWN BY CATEGORY
A30: PROFIT MARGIN TREND (%)
A44: KEY INSIGHTS & BUSINESS RECOMMENDATIONS
A45: Highest Margin Session | D45: 3 March session achieved 72.3% margin — lowest cost with full volume. Replicate supply planning.
A46: Banana Cost Risk | D46: 9 March: banana costs = 33.7% of total session cost. Negotiate bulk price or source alternative.
A47: Pricing Strategy | D47: Fixed price of Rp 4,000/cup across all sessions. Consider tiered pricing for premium variants.
A48: Volume Target | D48: Average 254 cups/session. Target 300 cups/session to improve fixed-cost absorption.
A49: Raw Material Dominance | D49: Raw materials = 63% of total cost. Bulk procurement and supplier negotiation are priority levers.
A50: Break-Even | D50: Break-even per session approximately Rp 160,000 (labor only). Achieved within first 40 cups sold.

Sheet Assumptions
A1: ASSUMPTIONS & OPERATIONAL NOTES
A2: All hardcoded inputs are shown in blue. Do not modify formula cells.
A4: FINANCIAL ASSUMPTIONS
A5: Parameter | B5: Value | C5: Notes | D5: Editable?
A6: Selling Price per Cup (Rp) | B6: 4000 | C6: Fixed across all sessions | D6: Yes
A7: Capacity Range (cups/session) | B7: 241-261 | C7: Demand-dependent | D7: Yes
A8: Profit Sharing with Partner | B8: 50% | C8: Split equally between 2 partners | D8: Yes
A9: Target Cups per Session | B9: 300 | C9: Management target for profitability | D9: Yes
A11: OPERATIONAL NOTES
A12: Parameter | B12: Value | C12: Notes | D12: Editable?
A13: Operating Days | B13: Each Ramadan session | C13: Update after each session | D13: No
A14: Consumables | B14: Sugar, Ice, Straw, Cup | C14: Purchased per session | D14: No
A15: Fixed Labor | B15: Rp 50,000 per session | C15: Operational assistant cost | D15: No
A16: Data Currency | B16: IDR (Indonesian Rupiah) | C16: No FX conversion required | D16: No
A18: COLOR CODING GUIDE
A19: Parameter | B19: Value | C19: Notes | D19: Editable?
A20: Blue text | B20: Hardcoded inputs / assumptions | C20: Values that can be changed by user | D20: No
A21: Black text | B21: Formulas / calculations | C21: Do not modify directly | D21: No
A22: Green text | B22: Cross-sheet formula links | C22: Pulls from other worksheets | D22: No
A23: Red text | B23: External file links | C23: Links to other workbooks | D23: No
